django_graphene_social_auth-1.1.1.dist-info/licenses/LICENSE
graphql_social_auth/__init__.py
graphql_social_auth/decorators.py
graphql_social_auth/exceptions.py
graphql_social_auth/mixins.py
graphql_social_auth/mutations.py
graphql_social_auth/types.py
graphql_social_auth/utils.py
graphql_social_auth/locale/es/LC_MESSAGES/django.mo
graphql_social_auth/locale/es/LC_MESSAGES/django.po
graphql_social_auth/relay/__init__.py
graphql_social_auth/relay/mutations.py
graphql_social_auth/relay/nodes.py
django_graphene_social_auth-1.1.1.dist-info/METADATA
django_graphene_social_auth-1.1.1.dist-info/WHEEL
django_graphene_social_auth-1.1.1.dist-info/top_level.txt
django_graphene_social_auth-1.1.1.dist-info/RECORD
