Metadata-Version: 2.4
Name: django-graphene-social-auth
Version: 1.1.1
Summary: Python Social Auth support for Django GraphQL
Home-page: https://github.com/Ademic2022/django-graphene-social-auth/
Author: Michael
Author-email: Michael <ademictech@gmail.com>, mongkok <domake.io@gmail.com>
Maintainer: Michael
Maintainer-email: Michael <ademictech@gmail.com>
License: The MIT License (MIT)
Project-URL: Homepage, https://github.com/Ademic2022/django-graphene-social-auth/
Project-URL: Repository, https://github.com/Ademic2022/django-graphene-social-auth/
Project-URL: Issues, https://github.com/Ademic2022/django-graphene-social-auth/issues
Classifier: Development Status :: 4 - Beta
Classifier: Environment :: Web Environment
Classifier: Intended Audience :: Developers
Classifier: Operating System :: OS Independent
Classifier: Programming Language :: Python
Classifier: Programming Language :: Python :: 3
Classifier: Programming Language :: Python :: 3.8
Classifier: Programming Language :: Python :: 3.9
Classifier: Programming Language :: Python :: 3.10
Classifier: Programming Language :: Python :: 3.11
Classifier: Programming Language :: Python :: 3.12
Classifier: Programming Language :: Python :: 3.13
Classifier: Framework :: Django
Classifier: Framework :: Django :: 3.2
Classifier: Framework :: Django :: 4.0
Classifier: Framework :: Django :: 4.1
Classifier: Framework :: Django :: 4.2
Classifier: Framework :: Django :: 5.0
Classifier: Framework :: Django :: 5.1
Requires-Python: >=3.8
License-File: LICENSE
Requires-Dist: Django>=3.2
Requires-Dist: graphene-django>=3.0.0
Requires-Dist: social-auth-app-django>=5.0.0
Requires-Dist: django-filter>=24.3
Provides-Extra: jwt
Requires-Dist: django-graphql-jwt>=0.4.0; extra == "jwt"
Provides-Extra: test
Requires-Dist: coverage>=7.0; extra == "test"
Requires-Dist: pytest>=7.0.0; extra == "test"
Requires-Dist: pytest-cov>=4.0.0; extra == "test"
Requires-Dist: pytest-django>=4.5.0; extra == "test"
Requires-Dist: pytest-asyncio>=0.21.0; extra == "test"
Dynamic: author
Dynamic: home-page
Dynamic: license-file
Dynamic: maintainer
